braintuner/__init__.py
braintuner-0.0.1.dist-info/LICENCE
braintuner-0.0.1.dist-info/METADATA
braintuner-0.0.1.dist-info/WHEEL
braintuner-0.0.1.dist-info/top_level.txt
braintuner-0.0.1.dist-info/RECORD
