Metadata-Version: 2.1
Name: braintuner
Version: 0.0.1
Summary: A brain tuner package
Home-page: https://github.com/luminoctum/braintuner
Author: Cheng Li
Author-email: cli@gps.caltech.edu
License: UNKNOWN
Platform: UNKNOWN
Classifier: Programming Language :: Python :: 3
Classifier: License :: OSI Approved :: MIT License
Classifier: Operating System :: OS Independent
Requires-Python: >=2.7
